sec_helpers/__init__.py
sec_helpers/cors_policy.py
sec_helpers/hsts.py
sec_helpers/no_http.py
sec_helpers/high_tls/__init__.py
sec_helpers/high_tls/protocol.py
sec_helpers/no_ssl/__init__.py
sec_helpers-0.3.3.dist-info/LICENSE
sec_helpers-0.3.3.dist-info/METADATA
sec_helpers-0.3.3.dist-info/WHEEL
sec_helpers-0.3.3.dist-info/top_level.txt
sec_helpers-0.3.3.dist-info/RECORD
