Metadata-Version: 2.1
Name: sec-helpers
Version: 0.3.3
Summary: DAST Security Helpers
Home-page: https://github.com/vwt-digital/sec-helpers/tree/master
Author: VWT Digital
Author-email: support@vwt.digital
License: gpl-3.0
Keywords: DAST,security,helpers,vwt
Platform: UNKNOWN
Classifier: Programming Language :: Python :: 3.6
Classifier: License :: OSI Approved :: GNU General Public License v3 (GPLv3)
Classifier: Operating System :: OS Independent
Classifier: Intended Audience :: Developers
Classifier: Natural Language :: English
Requires-Python: >=3.6
Requires-Dist: certifi (==2020.12.5)
Requires-Dist: chardet (==4.0.0)
Requires-Dist: idna (==2.10)
Requires-Dist: requests (==2.25.1)
Requires-Dist: urllib3 (==1.26.4)
